CHANGES
COPYING.LGPLv3
LICENSE
MANIFEST.in
README
ez_setup.py
requirements.txt
setup.py
configfield/__init__.py
configfield/dbfields.py
configfield/fields.py
configfield/params.py
configfield/widgets.py
configfield/templates/configfield/bool_widget.html
configfield/templates/configfield/list_widget.html
configfield/templates/configfield/param_widget.html
configfield/templates/configfield/text_widget.html
django_configfield.egg-info/PKG-INFO
django_configfield.egg-info/SOURCES.txt
django_configfield.egg-info/dependency_links.txt
django_configfield.egg-info/requires.txt
django_configfield.egg-info/top_level.txt